{"compressionlevel": -1, "editorsettings": {"chunksize": {"height": 32, "width": 32}, "export": {"format": "json", "target": "."}}, "height": 9, "infinite": false, "layers": [{"data": [38, 38, 38, 38, 38, 38, 38, 38, 38, 38, 38, 38, 38, 4162, 38, 38, 38, 38, 38, 38, 4162, 4162, 4162, 4162, 4162, 38, 38, 38, 38, 4162, 4162, 4162, 4162, 4162, 38, 38, 38, 4162, 4162, 4162, 4162, 4162, 4162, 4162, 38, 38, 38, 4162, 4162, 4162, 4162, 4162, 38, 38, 38, 38, 4162, 4162, 4162, 4162, 4162, 38, 38, 38, 38, 38, 38, 4162, 38, 38, 38, 38, 38, 38, 38, 38, 38, 38, 38, 38, 38], "height": 9, "id": 2, "name": "bottom", "opacity": 1, "type": "tilelayer", "visible": true, "width": 9, "x": 0, "y": 0}, {"data": [0, 0, 0, 0, 0, 0, 0, 0, 0, 0, 0, 0, 0, 0, 0, 0, 0, 0, 0, 0, 0, 0, 0, 0, 0, 0, 0, 0, 0, 0, 0, 0, 0, 0, 0, 0, 0, 0, 0, 0, 0, 0, 0, 0, 0, 0, 0, 3137, 0, 0, 0, 0, 0, 0, 0, 0, 3153, 0, 0, 0, 0, 0, 0, 0, 0, 0, 0, 0, 0, 0, 0, 0, 0, 0, 0, 0, 0, 0, 0, 0, 0], "height": 9, "id": 56, "name": "inventory22", "opacity": 1, "type": "tilelayer", "visible": false, "width": 9, "x": 0, "y": 0}, {"data": [0, 0, 0, 0, 0, 0, 0, 0, 0, 0, 0, 0, 0, 0, 0, 0, 0, 0, 0, 0, 0, 0, 0, 0, 0, 0, 0, 0, 0, 0, 0, 0, 0, 0, 0, 0, 0, 0, 0, 0, 10, 0, 0, 0, 0, 0, 0, 0, 0, 0, 0, 0, 0, 0, 0, 0, 0, 0, 0, 0, 0, 0, 0, 0, 0, 0, 0, 0, 0, 0, 0, 0, 0, 0, 0, 0, 0, 0, 0, 0, 0], "height": 9, "id": 11, "name": "start", "opacity": 0, "type": "tilelayer", "visible": true, "width": 9, "x": 0, "y": 0}, {"data": [0, 0, 0, 0, 0, 0, 0, 0, 0, 0, 0, 0, 0, 0, 0, 0, 0, 0, 0, 0, 0, 0, 0, 0, 0, 0, 0, 0, 0, 0, 0, 0, 0, 0, 0, 0, 0, 10, 0, 0, 0, 0, 0, 0, 0, 0, 0, 0, 0, 0, 0, 0, 0, 0, 0, 0, 0, 0, 0, 0, 0, 0, 0, 0, 0, 0, 0, 0, 0, 0, 0, 0, 0, 0, 0, 0, 0, 0, 0, 0, 0], "height": 9, "id": 27, "name": "exit4", "opacity": 0, "properties": [{"name": "exitUrl", "type": "string", "value": "fqfgzdmakfodryjgkqyhtpbwytvqqxsxjsoskorflywycnjjtxycbqnmfoju-fa7f2ff7-e90e-43d5-9aa8-acfdd94ffef3-17bfc3ac-e3bb-4dea-b6a8-61b69b0f6026-uysfnvxmixnepfy598.json"}], "type": "tilelayer", "visible": true, "width": 9, "x": 0, "y": 0}, {"data": [0, 0, 0, 0, 0, 0, 0, 0, 0, 0, 0, 0, 0, 0, 0, 0, 0, 0, 0, 0, 0, 0, 0, 0, 0, 0, 0, 0, 0, 0, 0, 0, 0, 0, 0, 0, 0, 0, 0, 0, 0, 0, 0, 0, 0, 0, 0, 0, 0, 0, 0, 0, 0, 0, 0, 0, 0, 0, 0, 0, 0, 0, 0, 0, 0, 0, 0, 10, 0, 0, 0, 0, 0, 0, 0, 0, 0, 0, 0, 0, 0], "height": 9, "id": 17, "name": "exit3", "opacity": 0, "properties": [{"name": "exitUrl", "type": "string", "value": "bwewjwpyqejmnqwuapxddrdtxlloqblmalvtezuxiaxzaomcwpxeqogsxzcb-33862cfe-f06a-4ce3-a222-9d76f866b1a7-399079d1-2cd2-4a23-a5e1-bfcad1244802-xkykdkiykyukvlx7176.json"}], "type": "tilelayer", "visible": true, "width": 9, "x": 0, "y": 0}, {"data": [0, 0, 0, 0, 0, 0, 0, 0, 0, 0, 0, 0, 0, 0, 0, 0, 0, 0, 0, 0, 0, 0, 0, 0, 0, 0, 0, 0, 0, 0, 0, 0, 0, 0, 0, 0, 0, 0, 0, 0, 0, 0, 0, 10, 0, 0, 0, 0, 0, 0, 0, 0, 0, 0, 0, 0, 0, 0, 0, 0, 0, 0, 0, 0, 0, 0, 0, 0, 0, 0, 0, 0, 0, 0, 0, 0, 0, 0, 0, 0, 0], "height": 9, "id": 16, "name": "exit2", "opacity": 0, "properties": [{"name": "exitUrl", "type": "string", "value": "xnbxjrlxybxknovosxqwahwrkrpfxecbpprolwwdmumzgztskizoaxkalyzj-ca01d883-e13f-4e78-af6c-dd9ad571e122-d3433d69-ebc8-4673-9f12-d699460efbba-uqbckgbfwdiynjg9035.json"}], "type": "tilelayer", "visible": true, "width": 9, "x": 0, "y": 0}, {"data": [0, 0, 0, 0, 0, 0, 0, 0, 0, 0, 0, 0, 0, 10, 0, 0, 0, 0, 0, 0, 0, 0, 0, 0, 0, 0, 0, 0, 0, 0, 0, 0, 0, 0, 0, 0, 0, 0, 0, 0, 0, 0, 0, 0, 0, 0, 0, 0, 0, 0, 0, 0, 0, 0, 0, 0, 0, 0, 0, 0, 0, 0, 0, 0, 0, 0, 0, 0, 0, 0, 0, 0, 0, 0, 0, 0, 0, 0, 0, 0, 0], "height": 9, "id": 20, "name": "exit1", "opacity": 0, "properties": [{"name": "exitUrl", "type": "string", "value": "yonrterzfwdviihmpnmxbrvtleucvtphdxxsooqgtbdnnadcqlxtvwpbxeuu-44522c72-d4a7-4bdf-9dc9-35a87e169636-9e4500a6-8270-4e37-a9b4-2a0907e1a693-xvqrhjzfcpntjsf4316.json"}], "type": "tilelayer", "visible": true, "width": 9, "x": 0, "y": 0}, {"draworder": "topdown", "id": 3, "name": "floorLayer", "objects": [], "opacity": 1, "type": "objectgroup", "visible": true, "x": 0, "y": 0}], "nextlayerid": 30, "nextobjectid": 9, "orientation": "orthogonal", "renderorder": "right-down", "tiledversion": "1.4.2", "tileheight": 32, "tilesets": [{"columns": 8, "firstgid": 1, "image": "../tiles/imgs/tilesheets/floortileset.png", "imageheight": 256, "imagewidth": 256, "margin": 0, "name": "floortileset", "spacing": 0, "tilecount": 64, "tileheight": 32, "tiles": [{"id": 37, "properties": [{"name": "collides", "type": "bool", "value": true}]}], "tilewidth": 32}, {"columns": 16, "firstgid": 65, "image": "../tiles/imgs/tilesheets/cert_safety.png", "imageheight": 2048, "imagewidth": 512, "margin": 0, "name": "cert_safety", "spacing": 0, "tilecount": 1024, "tileheight": 32, "tilewidth": 32}, {"columns": 16, "firstgid": 1089, "image": "../tiles/imgs/tilesheets/cert.png", "imageheight": 2048, "imagewidth": 512, "margin": 0, "name": "cert", "spacing": 0, "tilecount": 1024, "tileheight": 32, "tilewidth": 32}, {"columns": 16, "firstgid": 2113, "image": "../tiles/imgs/tilesheets/food_and_drinks.png", "imageheight": 2048, "imagewidth": 512, "margin": 0, "name": "food_and_drinks", "spacing": 0, "tilecount": 1024, "tileheight": 32, "tilewidth": 32}, {"columns": 16, "firstgid": 3137, "image": "../tiles/imgs/tilesheets/furniture.png", "imageheight": 2048, "imagewidth": 512, "margin": 0, "name": "furniture", "spacing": 0, "tilecount": 1024, "tileheight": 32, "tilewidth": 32}, {"columns": 16, "firstgid": 4161, "image": "../tiles/imgs/tilesheets/leipzig_messe.png", "imageheight": 2048, "imagewidth": 512, "margin": 0, "name": "leipzig_messe", "spacing": 0, "tilecount": 1024, "tileheight": 32, "tiles": [{"id": 15, "properties": [{"name": "collides", "type": "bool", "value": true}]}, {"id": 31, "properties": [{"name": "collides", "type": "bool", "value": true}]}, {"id": 47, "properties": [{"name": "collides", "type": "bool", "value": true}]}, {"id": 63, "properties": [{"name": "collides", "type": "bool", "value": true}]}], "tilewidth": 32}, {"columns": 16, "firstgid": 5185, "image": "../tiles/imgs/tilesheets/misc.png", "imageheight": 2048, "imagewidth": 512, "margin": 0, "name": "misc", "spacing": 0, "tilecount": 1024, "tileheight": 32, "tiles": [{"animation": [{"duration": 300, "tileid": 57}, {"duration": 300, "tileid": 58}, {"duration": 300, "tileid": 59}, {"duration": 300, "tileid": 58}], "id": 57}], "tilewidth": 32}, {"columns": 16, "firstgid": 6209, "image": "../tiles/imgs/tilesheets/storage.png", "imageheight": 2048, "imagewidth": 512, "margin": 0, "name": "storage", "spacing": 0, "tilecount": 1024, "tileheight": 32, "tilewidth": 32}], "tilewidth": 32, "type": "map", "version": 1.4, "width": 9}