{"compressionlevel": -1, "editorsettings": {"chunksize": {"height": 32, "width": 32}, "export": {"format": "json", "target": "."}}, "height": 9, "infinite": false, "layers": [{"data": [38, 38, 38, 38, 38, 38, 38, 38, 38, 38, 38, 38, 38, 49, 38, 38, 38, 38, 38, 38, 49, 49, 49, 49, 49, 38, 38, 38, 38, 49, 49, 49, 49, 49, 38, 38, 38, 49, 49, 49, 49, 49, 49, 49, 38, 38, 38, 49, 49, 49, 49, 49, 38, 38, 38, 38, 49, 49, 49, 49, 49, 38, 38, 38, 38, 38, 38, 49, 38, 38, 38, 38, 38, 38, 38, 38, 38, 38, 38, 38, 38], "height": 9, "id": 2, "name": "bottom", "opacity": 1, "type": "tilelayer", "visible": true, "width": 9, "x": 0, "y": 0}, {"data": [0, 0, 0, 0, 0, 0, 0, 0, 0, 0, 0, 0, 0, 0, 0, 0, 0, 0, 0, 0, 0, 0, 0, 0, 0, 0, 0, 0, 0, 0, 0, 0, 0, 0, 0, 0, 0, 0, 0, 0, 0, 0, 0, 0, 0, 0, 0, 3137, 0, 0, 0, 0, 0, 0, 0, 0, 3153, 0, 0, 0, 0, 0, 0, 0, 0, 0, 0, 0, 0, 0, 0, 0, 0, 0, 0, 0, 0, 0, 0, 0, 0], "height": 9, "id": 56, "name": "inventory22", "opacity": 1, "type": "tilelayer", "visible": false, "width": 9, "x": 0, "y": 0}, {"data": [0, 0, 0, 0, 0, 0, 0, 0, 0, 0, 0, 0, 0, 0, 0, 0, 0, 0, 0, 0, 0, 0, 0, 0, 0, 0, 0, 0, 0, 0, 0, 0, 0, 0, 0, 0, 0, 0, 0, 0, 10, 0, 0, 0, 0, 0, 0, 0, 0, 0, 0, 0, 0, 0, 0, 0, 0, 0, 0, 0, 0, 0, 0, 0, 0, 0, 0, 0, 0, 0, 0, 0, 0, 0, 0, 0, 0, 0, 0, 0, 0], "height": 9, "id": 11, "name": "start", "opacity": 0, "type": "tilelayer", "visible": true, "width": 9, "x": 0, "y": 0}, {"data": [0, 0, 0, 0, 0, 0, 0, 0, 0, 0, 0, 0, 0, 0, 0, 0, 0, 0, 0, 0, 0, 0, 0, 0, 0, 0, 0, 0, 0, 0, 0, 0, 0, 0, 0, 0, 0, 10, 0, 0, 0, 0, 0, 0, 0, 0, 0, 0, 0, 0, 0, 0, 0, 0, 0, 0, 0, 0, 0, 0, 0, 0, 0, 0, 0, 0, 0, 0, 0, 0, 0, 0, 0, 0, 0, 0, 0, 0, 0, 0, 0], "height": 9, "id": 27, "name": "exit4", "opacity": 0, "properties": [{"name": "exitUrl", "type": "string", "value": "wfemrroudythmhvygrmidqzkwuylpgrqmofsmkrtjsnuceppdfaahvvjqhts-3303d8cc-6b21-4190-b08a-b24d3ef174a9-2009bc28-ae7f-4528-8ad6-4e81f08fccd2-oxldmufikohzrlc1456.json"}], "type": "tilelayer", "visible": true, "width": 9, "x": 0, "y": 0}, {"data": [0, 0, 0, 0, 0, 0, 0, 0, 0, 0, 0, 0, 0, 0, 0, 0, 0, 0, 0, 0, 0, 0, 0, 0, 0, 0, 0, 0, 0, 0, 0, 0, 0, 0, 0, 0, 0, 0, 0, 0, 0, 0, 0, 0, 0, 0, 0, 0, 0, 0, 0, 0, 0, 0, 0, 0, 0, 0, 0, 0, 0, 0, 0, 0, 0, 0, 0, 10, 0, 0, 0, 0, 0, 0, 0, 0, 0, 0, 0, 0, 0], "height": 9, "id": 17, "name": "exit3", "opacity": 0, "properties": [{"name": "exitUrl", "type": "string", "value": "fuqhxslisszdlpqjopovumfjxcglkzlodrcbwglkpeyrafqffwytzbvaixth-dcd21d70-b3ee-46c2-8e9a-37389bd5f138-e8a69d29-f5b5-488c-b36d-a51fea9f0ace-ppdydxkzgguogmf10114.json"}], "type": "tilelayer", "visible": true, "width": 9, "x": 0, "y": 0}, {"data": [0, 0, 0, 0, 0, 0, 0, 0, 0, 0, 0, 0, 0, 0, 0, 0, 0, 0, 0, 0, 0, 0, 0, 0, 0, 0, 0, 0, 0, 0, 0, 0, 0, 0, 0, 0, 0, 0, 0, 0, 0, 0, 0, 10, 0, 0, 0, 0, 0, 0, 0, 0, 0, 0, 0, 0, 0, 0, 0, 0, 0, 0, 0, 0, 0, 0, 0, 0, 0, 0, 0, 0, 0, 0, 0, 0, 0, 0, 0, 0, 0], "height": 9, "id": 16, "name": "exit2", "opacity": 0, "properties": [{"name": "exitUrl", "type": "string", "value": "emoqocwyakonspjwrvxwmtibgbzphfhmegwemtseckhvuuoynyobtlimutxo-4d3d09c4-a6b3-4728-8c8b-a4c5c369b107-f46ee4ef-de03-4b9d-bd1b-6dd109c8ad36-earhlrjoqhrkgoy3913.json"}], "type": "tilelayer", "visible": true, "width": 9, "x": 0, "y": 0}, {"data": [0, 0, 0, 0, 0, 0, 0, 0, 0, 0, 0, 0, 0, 10, 0, 0, 0, 0, 0, 0, 0, 0, 0, 0, 0, 0, 0, 0, 0, 0, 0, 0, 0, 0, 0, 0, 0, 0, 0, 0, 0, 0, 0, 0, 0, 0, 0, 0, 0, 0, 0, 0, 0, 0, 0, 0, 0, 0, 0, 0, 0, 0, 0, 0, 0, 0, 0, 0, 0, 0, 0, 0, 0, 0, 0, 0, 0, 0, 0, 0, 0], "height": 9, "id": 20, "name": "exit1", "opacity": 0, "properties": [{"name": "exitUrl", "type": "string", "value": "emoqocwyakonspjwrvxwmtibgbzphfhmegwemtseckhvuuoynyobtlimutxo-7c37accb-967c-4b4a-b456-7b0d4a5d39f7-d9c02601-af30-4544-bdea-5788f9748117-onbqaucwrqvsjrb5057.json"}], "type": "tilelayer", "visible": true, "width": 9, "x": 0, "y": 0}, {"draworder": "topdown", "id": 3, "name": "floorLayer", "objects": [], "opacity": 1, "type": "objectgroup", "visible": true, "x": 0, "y": 0}, {"data": [0, 0, 0, 0, 0, 0, 0, 0, 0, 0, 0, 0, 0, 0, 0, 0, 0, 0, 0, 0, 0, 0, 0, 0, 0, 0, 0, 0, 0, 0, 0, 0, 0, 0, 0, 0, 0, 0, 0, 0, 0, 0, 0, 0, 0, 0, 0, 0, 0, 0, 0, 0, 0, 0, 0, 0, 0, 0, 0, 0, 0, 0, 0, 0, 0, 0, 0, 0, 0, 0, 0, 0, 0, 0, 0, 0, 0, 0, 0, 0, 0], "height": 9, "id": 7, "name": "override", "opacity": 1, "properties": [{"name": "depth", "type": "int", "value": 3}], "type": "tilelayer", "visible": true, "width": 9, "x": 0, "y": 0}], "nextlayerid": 28, "nextobjectid": 9, "orientation": "orthogonal", "renderorder": "right-down", "tiledversion": "1.4.2", "tileheight": 32, "tilesets": [{"columns": 8, "firstgid": 1, "image": "../tiles/imgs/tilesheets/floortileset.png", "imageheight": 256, "imagewidth": 256, "margin": 0, "name": "floortileset", "spacing": 0, "tilecount": 64, "tileheight": 32, "tiles": [{"id": 37, "properties": [{"name": "collides", "type": "bool", "value": true}]}], "tilewidth": 32}, {"columns": 16, "firstgid": 65, "image": "../tiles/imgs/tilesheets/cert_safety.png", "imageheight": 2048, "imagewidth": 512, "margin": 0, "name": "cert_safety", "spacing": 0, "tilecount": 1024, "tileheight": 32, "tilewidth": 32}, {"columns": 16, "firstgid": 1089, "image": "../tiles/imgs/tilesheets/cert.png", "imageheight": 2048, "imagewidth": 512, "margin": 0, "name": "cert", "spacing": 0, "tilecount": 1024, "tileheight": 32, "tilewidth": 32}, {"columns": 16, "firstgid": 2113, "image": "../tiles/imgs/tilesheets/food_and_drinks.png", "imageheight": 2048, "imagewidth": 512, "margin": 0, "name": "food_and_drinks", "spacing": 0, "tilecount": 1024, "tileheight": 32, "tilewidth": 32}, {"columns": 16, "firstgid": 3137, "image": "../tiles/imgs/tilesheets/furniture.png", "imageheight": 2048, "imagewidth": 512, "margin": 0, "name": "furniture", "spacing": 0, "tilecount": 1024, "tileheight": 32, "tilewidth": 32}, {"columns": 16, "firstgid": 4161, "image": "../tiles/imgs/tilesheets/leipzig_messe.png", "imageheight": 2048, "imagewidth": 512, "margin": 0, "name": "leipzig_messe", "spacing": 0, "tilecount": 1024, "tileheight": 32, "tiles": [{"id": 15, "properties": [{"name": "collides", "type": "bool", "value": true}]}, {"id": 31, "properties": [{"name": "collides", "type": "bool", "value": true}]}, {"id": 47, "properties": [{"name": "collides", "type": "bool", "value": true}]}, {"id": 63, "properties": [{"name": "collides", "type": "bool", "value": true}]}], "tilewidth": 32}, {"columns": 16, "firstgid": 5185, "image": "../tiles/imgs/tilesheets/misc.png", "imageheight": 2048, "imagewidth": 512, "margin": 0, "name": "misc", "spacing": 0, "tilecount": 1024, "tileheight": 32, "tiles": [{"animation": [{"duration": 300, "tileid": 57}, {"duration": 300, "tileid": 58}, {"duration": 300, "tileid": 59}, {"duration": 300, "tileid": 58}], "id": 57}], "tilewidth": 32}, {"columns": 16, "firstgid": 6209, "image": "../tiles/imgs/tilesheets/storage.png", "imageheight": 2048, "imagewidth": 512, "margin": 0, "name": "storage", "spacing": 0, "tilecount": 1024, "tileheight": 32, "tilewidth": 32}], "tilewidth": 32, "type": "map", "version": 1.4, "width": 9}